artifetch/__init__.py
artifetch/cli.py
artifetch/core.py
artifetch/providers/__init__.py
artifetch/providers/artifactory.py
artifetch/providers/git.py
artifetch/providers/gitlab.py
artifetch/utils/filesystem.py
artifetch-0.0.7.dist-info/licenses/LICENSE.txt
artifetch-0.0.7.dist-info/METADATA
artifetch-0.0.7.dist-info/WHEEL
artifetch-0.0.7.dist-info/entry_points.txt
artifetch-0.0.7.dist-info/top_level.txt
artifetch-0.0.7.dist-info/RECORD
