Metadata-Version: 2.4
Name: artifetch
Version: 0.0.7
Summary: Universal artifact fetcher for Artifactory, GitLab, and Git.
Author: Gemma Mcgee
Project-URL: Homepage, https://github.com/gemmamary/artifetch/
Project-URL: Documentation, https://github.com/gemmamary/artifetch/#README.md
License-File: LICENSE.txt
Requires-Dist: requests
Requires-Dist: python-gitlab
Requires-Dist: python-dotenv
Provides-Extra: dev
Requires-Dist: build; extra == "dev"
Requires-Dist: twine; extra == "dev"
Requires-Dist: setuptools; extra == "dev"
Requires-Dist: setuptools_scm; extra == "dev"
Requires-Dist: wheel; extra == "dev"
Requires-Dist: deptry; extra == "dev"
Requires-Dist: pytest; extra == "dev"
Requires-Dist: ruff; extra == "dev"
Requires-Dist: black; extra == "dev"
Requires-Dist: mypy; extra == "dev"
Dynamic: license-file
